auklet/__about__.py
auklet/__init__.py
auklet/apps.py
auklet/broker.py
auklet/client.py
auklet/errors.py
auklet/middleware.py
auklet/stats.py
auklet/utils.py
auklet/licenses/auklet
auklet/monitoring/__init__.py
auklet/monitoring/logging.py
django_auklet-0.5.0.dist-info/LICENSE
django_auklet-0.5.0.dist-info/METADATA
django_auklet-0.5.0.dist-info/WHEEL
django_auklet-0.5.0.dist-info/top_level.txt
django_auklet-0.5.0.dist-info/RECORD
