Metadata-Version: 2.1
Name: django-auklet
Version: 0.5.0
Summary: Auklet performance monitoring agent for Django apps
Home-page: https://github.com/aukletio/Auklet-Agent-Django
Author: Auklet
Author-email: hello@auklet.io
License: Apache
Keywords: iot,performance,monitoring,problem solving
Platform: linux
Classifier: Development Status :: 4 - Beta
Classifier: Environment :: Console
Classifier: Intended Audience :: Developers
Classifier: License :: OSI Approved :: Apache Software License
Classifier: Operating System :: POSIX :: Linux
Classifier: Programming Language :: Python
Classifier: Programming Language :: Python :: 2
Classifier: Programming Language :: Python :: 2.7
Classifier: Programming Language :: Python :: 3
Classifier: Programming Language :: Python :: 3.4
Classifier: Programming Language :: Python :: 3.5
Classifier: Programming Language :: Python :: 3.6
Classifier: Programming Language :: Python :: 3.7
Classifier: Programming Language :: Python :: Implementation :: CPython
Classifier: Programming Language :: Python :: Implementation :: PyPy
Classifier: Topic :: Software Development :: Debuggers
Requires-Dist: six (>=1.8.0)
Requires-Dist: paho-mqtt (==1.3.1)
Requires-Dist: psutil (==5.4.5)
Requires-Dist: pidigits (==0.5)
Requires-Dist: mock (==2.0.0)
Requires-Dist: requests
Requires-Dist: msgpack (==0.5.6)
